.coveragerc
.mailmap
.testr.conf
AUTHORS
CONTRIBUTING.rst
ChangeLog
HACKING.rst
LICENSE
MANIFEST.in
README.rst
babel.cfg
requirements.txt
setup.cfg
setup.py
test-requirements.txt
tox.ini
doc/source/conf.py
doc/source/contributing.rst
doc/source/index.rst
doc/source/installation.rst
doc/source/readme.rst
doc/source/usage.rst
mqtt_statsd/__init__.py
mqtt_statsd/daemon.py
mqtt_statsd.egg-info/PKG-INFO
mqtt_statsd.egg-info/SOURCES.txt
mqtt_statsd.egg-info/dependency_links.txt
mqtt_statsd.egg-info/entry_points.txt
mqtt_statsd.egg-info/not-zip-safe
mqtt_statsd.egg-info/pbr.json
mqtt_statsd.egg-info/requires.txt
mqtt_statsd.egg-info/top_level.txt
mqtt_statsd/tests/__init__.py
mqtt_statsd/tests/base.py
mqtt_statsd/tests/test_mqtt_statsd.py
releasenotes/notes/.placeholder
releasenotes/source/conf.py
releasenotes/source/index.rst
releasenotes/source/unreleased.rst
releasenotes/source/_static/.placeholder
releasenotes/source/_templates/.placeholder