Metadata-Version: 1.1
Name: mqtt-statsd
Version: 0.0.1
Summary: A script to publish MQTT metrics into statsd
Home-page: http://www.openstack.org/
Author: Matthew Treinish
Author-email: mtreinish@kortar.org
License: UNKNOWN
Platform: UNKNOWN
Classifier: Environment :: OpenStack
Classifier: Intended Audience :: Information Technology
Classifier: Intended Audience :: System Administrators
Classifier: License :: OSI Approved :: Apache Software License
Classifier: Programming Language :: Python
Classifier: Programming Language :: Python :: 2
Classifier: Programming Language :: Python :: 2.7
Classifier: Programming Language :: Python :: 3
Classifier: Programming Language :: Python :: 3.5
Classifier: Programming Language :: Python :: 3.6
